algo_gen/__init__.py
algo_gen/classes.py
algo_gen/individuals/STS.py
algo_gen/individuals/__init__.py
algo_gen/individuals/onemax.py
algo_gen/tools/__init__.py
algo_gen/tools/gridsearch.py
algo_gen/tools/plot.py
algo_gen/tools/tools.py
algo_gen-0.15.dist-info/LICENSE
algo_gen-0.15.dist-info/METADATA
algo_gen-0.15.dist-info/WHEEL
algo_gen-0.15.dist-info/top_level.txt
algo_gen-0.15.dist-info/RECORD
