Metadata-Version: 2.1
Name: algo-gen
Version: 0.15
Summary: Genetic Algorithm
Home-page: https://github.com/Cyril-Grl/AlgoGen
Author: Cyril-Grl
License: UNKNOWN
Platform: UNKNOWN
Classifier: Development Status :: 3 - Alpha
Classifier: Programming Language :: Python :: 3
Classifier: License :: OSI Approved :: MIT License
Classifier: Operating System :: OS Independent
Requires-Python: >=3.6
Requires-Dist: seaborn
Requires-Dist: numpy
Requires-Dist: matplotlib
